pypesa/__init__.py
pypesa/defaults.py
pypesa/open_api.py
pypesa/vodacom.py
pypesa-0.0.3.dist-info/LICENSE
pypesa-0.0.3.dist-info/WHEEL
pypesa-0.0.3.dist-info/METADATA
pypesa-0.0.3.dist-info/RECORD
