Metadata-Version: 2.1
Name: pypesa
Version: 0.0.3
Summary: Python Implementation for Mobile payments integrations.
Home-page: https://github.com/openpesa/pypesa.git
Keywords: develpoment,online payments,mobile payments
Author: Innocent Zenda
Author-email: zendainnocent@gmail.com
Requires-Python: >=3.7,<4.0
Classifier: Intended Audience :: Developers
Classifier: License :: OSI Approved :: MIT License
Classifier: Operating System :: OS Independent
Classifier: Programming Language :: Python :: 3
Classifier: Programming Language :: Python :: 3.7
Classifier: Programming Language :: Python :: 3.8
Classifier: Programming Language :: Python :: 3.9
Classifier: Topic :: Software Development :: Build Tools
Requires-Dist: pycryptodome (>=3.9.9,<4.0.0)
Requires-Dist: requests (>=2.25.0,<3.0.0)
Project-URL: Repository, https://github.com/openpesa/pypesa.git
